[
  {
    "id": 3,
    "text": "текст1",
    "date": 1771515370
  },
  {
    "id": 2,
    "text": "Хайпротек будет участвовать и иметь свой стенд на предстоящей 25-ой международной выставке «Оборудование и технологии для нефтегазового комплекса» Нефтегаз 2026 в МВЦ «Крокус Экспо». \n«Выставка «Нефтегаз» входит в десятку крупнейших нефтегазовых смотров мира, проводится ежегодно вместе с Национальным нефтегазовым форумом».\n На стенде ООО «Хайпротек», расположенном в 6 зале второго павильона (6D110) будет представлена наша новая технология MudVisionRT, за ним мы ответим на все ваши вопросы, обговорим инициативы, и, возможно, начнём новые партнёрские взаимоотношения. Это не первое и не последнее участие Хайпротек в выставке, но оно критически важно для нас. Следите за обновлениями! Форум пройдёт со 2 по 5 марта этого года.",
    "date": 1771514325
  }
]